bevyframe/__init__.py
bevyframe/cmdline.py
bevyframe/Features/Database.py
bevyframe/Features/Login.py
bevyframe/Features/Style.py
bevyframe/Frame/__init__.py
bevyframe/Frame/default_logging.py
bevyframe/Frame/error_handler.py
bevyframe/Frame/route.py
bevyframe/Frame/Run/Booting.py
bevyframe/Frame/Run/Receiver.py
bevyframe/Frame/Run/Responser.py
bevyframe/Frame/Run/Sender.py
bevyframe/Frame/Run/WSGI_Receiver.py
bevyframe/Helpers/Exceptions.py
bevyframe/Helpers/Identifiers.py
bevyframe/Helpers/LazyInitDict.py
bevyframe/Helpers/MatchRouting.py
bevyframe/Helpers/RenderCSS.py
bevyframe/Objects/Context.py
bevyframe/Objects/Response.py
bevyframe/Widgets/Page.py
bevyframe/Widgets/Style.py
bevyframe/Widgets/Widget.py
bevyframe/Widgets/Templates/Containers.py
bevyframe/Widgets/Templates/Inputs.py
bevyframe/Widgets/Templates/Media.py
bevyframe/Widgets/Templates/Navbar.py
bevyframe/Widgets/Templates/Texts.py
bevyframe/Widgets/Templates/__init__.py
BevyFrame-0.5.0.dist-info/LICENSE
BevyFrame-0.5.0.dist-info/METADATA
BevyFrame-0.5.0.dist-info/WHEEL
BevyFrame-0.5.0.dist-info/entry_points.txt
BevyFrame-0.5.0.dist-info/top_level.txt
BevyFrame-0.5.0.dist-info/RECORD
