Metadata-Version: 2.1
Name: BevyFrame
Version: 0.5.0
Summary: Python Web Framework
Maintainer-email: Çağan Mert İŞLEK <islekcaganmert@gmail.com>
License: LGPL-2.1
Project-URL: Homepage, https://bevyframe.islekcaganmert.me
Project-URL: Donate, https://www.buymeacoffee.com/islekcaganmert
Project-URL: Documentation, https://bevyframe.islekcaganmert.me/docs
Project-URL: Changes, https://bevyframe.islekcaganmert.me/changes
Project-URL: Source Code, https://github.com/islekcaganmert/bevyframe
Project-URL: Issue Tracker, https://github.com/islekcaganmert/bevyframe/issues
Project-URL: Chat, https://lemmy.today/c/bevyframe
Classifier: Environment :: Web Environment
Classifier: Intended Audience :: Developers
Classifier: Operating System :: OS Independent
Classifier: Programming Language :: Python
Classifier: Topic :: Internet :: WWW/HTTP :: Dynamic Content
Classifier: Topic :: Software Development :: Libraries :: Application Frameworks
Requires-Python: >=3.9
License-File: LICENSE
Requires-Dist: requests==2.32.3
Requires-Dist: Jinja2==3.1.4
Requires-Dist: gunicorn==23.0.0
Requires-Dist: hereus-ui-3-2==3.2.0
Requires-Dist: pycparser==2.22
Requires-Dist: typing-extensions==4.12.2
Requires-Dist: certifi==2024.8.30
Requires-Dist: cffi==1.17.1
Requires-Dist: PyJWT==2.9.0
Requires-Dist: charset-normalizer==3.4.0
Requires-Dist: cryptography==43.0.3
Requires-Dist: idna==3.10
Requires-Dist: urllib3==2.2.3
Requires-Dist: MarkupSafe==3.0.2
Requires-Dist: SQLAlchemy==2.0.36
Requires-Dist: TheProtocols==3.1.0.1
